noise2vst/__init__.py
noise2vst/models/__init__.py
noise2vst/models/drunet.py
noise2vst/models/ffdnet.py
noise2vst/models/noise2vst.py
noise2vst/pretrained_weights/download.py
noise2vst/utilities/__init__.py
noise2vst/utilities/utilities.py
noise2vst-0.1.0.dist-info/licenses/LICENSE
noise2vst-0.1.0.dist-info/METADATA
noise2vst-0.1.0.dist-info/WHEEL
noise2vst-0.1.0.dist-info/top_level.txt
noise2vst-0.1.0.dist-info/RECORD
