Metadata-Version: 2.4
Name: Noise2VST
Version: 0.1.0
Summary: Noise2VST denoising microscopy images
Author-email: Sébastien Herbreteau <sebastien.herbreteau@ensai.fr>
Maintainer-email: Ibrahima Alain Gueye <gueyeibrahimaalain@gmail.com>
Classifier: Programming Language :: Python :: 3
Classifier: Programming Language :: Python :: 3.10
Classifier: Programming Language :: Python :: 3.11
Classifier: Topic :: Scientific/Engineering :: Image Processing
Requires-Python: >=3.10
License-File: LICENSE
Requires-Dist: torch
Requires-Dist: torchvision
Dynamic: license-file
